{"_type":"export","__export_format":4,"__export_date":"2024-04-26T20:27:04.559Z","__export_source":"insomnia.desktop.app:v9.0.0","resources":[{"_id":"req_798e4dc9a1a64d5daee266c61c0dfc92","parentId":"wrk_0d9db9250da5438aab4956e39e8371c3","modified":1714149761106,"created":1713985154898,"url":"http://localhost:3000/api/forums/13/sujets","name":"forums/id/sujets","description":"","method":"GET","body":{},"preRequestScript":"","parameters":[],"headers":[{"name":"User-Agent","value":"insomnia/8.6.1"}],"authentication":{},"metaSortKey":-1711133343272.75,"isPrivate":false,"pathParameters":[],"settingStoreCookies":true,"settingSendCookies":true,"settingDisableRenderRequestBody":false,"settingEncodeUrl":true,"settingRebuildPath":true,"settingFollowRedirects":"global","_type":"request"},{"_id":"wrk_0d9db9250da5438aab4956e39e8371c3","parentId":null,"modified":1711557182275,"created":1711557182275,"name":"Forum NuxtJS","description":"","scope":"collection","_type":"workspace"},{"_id":"req_325f2159e6f843b6957fd869705a05f1","parentId":"wrk_0d9db9250da5438aab4956e39e8371c3","modified":1711717993538,"created":1711640759448,"url":"http://localhost:3000/api/forums/1","name":"forums id","description":"","method":"GET","body":{},"preRequestScript":"","parameters":[],"headers":[{"name":"User-Agent","value":"insomnia/8.6.1"}],"authentication":{},"metaSortKey":-1711174360645,"isPrivate":false,"pathParameters":[],"settingStoreCookies":true,"settingSendCookies":true,"settingDisableRenderRequestBody":false,"settingEncodeUrl":true,"settingRebuildPath":true,"settingFollowRedirects":"global","_type":"request"},{"_id":"req_6a449f3732b54433b0cd17a3c98195ba","parentId":"wrk_0d9db9250da5438aab4956e39e8371c3","modified":1713987207368,"created":1713986530421,"url":"http://localhost:3000/api/sujets/1/messages/2","name":"delete message (sujet/id/messages/id)","description":"","method":"DELETE","body":{"mimeType":"application/json","text":""},"preRequestScript":"","parameters":[],"headers":[{"name":"Content-Type","value":"application/json"},{"name":"User-Agent","value":"insomnia/8.6.1"}],"authentication":{},"metaSortKey":-1711181196865.375,"isPrivate":false,"pathParameters":[],"settingStoreCookies":true,"settingSendCookies":true,"settingDisableRenderRequestBody":false,"settingEncodeUrl":true,"settingRebuildPath":true,"settingFollowRedirects":"global","_type":"request"},{"_id":"req_777955e3a8b348adae43c5f278b535f8","parentId":"wrk_0d9db9250da5438aab4956e39e8371c3","modified":1713985347354,"created":1713984923358,"url":"http://localhost:3000/api/sujets/1/messages/1","name":"update message (sujet/id/messages/id)","description":"","method":"POST","body":{"mimeType":"application/json","text":"{\n\t\"content\":\"Salut, je suis en train de modifier le contenu du message 1\"\n}"},"preRequestScript":"","parameters":[],"headers":[{"name":"Content-Type","value":"application/json"},{"name":"User-Agent","value":"insomnia/8.6.1"}],"authentication":{},"metaSortKey":-1711188033085.75,"isPrivate":false,"pathParameters":[],"settingStoreCookies":true,"settingSendCookies":true,"settingDisableRenderRequestBody":false,"settingEncodeUrl":true,"settingRebuildPath":true,"settingFollowRedirects":"global","_type":"request"},{"_id":"req_63693d6cb9234f6a9a1ead47489b80b9","parentId":"wrk_0d9db9250da5438aab4956e39e8371c3","modified":1713892913677,"created":1711721963701,"url":"http://localhost:3000/api/sujets/1/messages?page=8","name":"sujet/id/messages","description":"","method":"GET","body":{},"preRequestScript":"","parameters":[],"headers":[{"name":"User-Agent","value":"insomnia/8.6.1"}],"authentication":{},"metaSortKey":-1711201705526.5,"isPrivate":false,"pathParameters":[],"settingStoreCookies":true,"settingSendCookies":true,"settingDisableRenderRequestBody":false,"settingEncodeUrl":true,"settingRebuildPath":true,"settingFollowRedirects":"global","_type":"request"},{"_id":"req_5eda4e21fcae4967861ccbc4c9386dc5","parentId":"wrk_0d9db9250da5438aab4956e39e8371c3","modified":1713985070813,"created":1711620775022,"url":"http://localhost:3000/api/sujets/3","name":"sujet/id","description":"","method":"GET","body":{},"preRequestScript":"","parameters":[],"headers":[{"name":"User-Agent","value":"insomnia/8.6.1"}],"authentication":{},"metaSortKey":-1711229050408,"isPrivate":false,"pathParameters":[],"settingStoreCookies":true,"settingSendCookies":true,"settingDisableRenderRequestBody":false,"settingEncodeUrl":true,"settingRebuildPath":true,"settingFollowRedirects":"global","_type":"request"},{"_id":"req_3b6071ea7a7244b7bf81cb13ce558c63","parentId":"wrk_0d9db9250da5438aab4956e39e8371c3","modified":1713985078329,"created":1711561059144,"url":"http://localhost:3000/api/users/user","name":"users/id","description":"","method":"GET","body":{},"preRequestScript":"","parameters":[],"headers":[{"name":"User-Agent","value":"insomnia/8.6.1"}],"authentication":{},"metaSortKey":-1711338429934,"isPrivate":false,"pathParameters":[],"settingStoreCookies":true,"settingSendCookies":true,"settingDisableRenderRequestBody":false,"settingEncodeUrl":true,"settingRebuildPath":true,"settingFollowRedirects":"global","_type":"request"},{"_id":"req_4fd17e552713401f83ba6af157e75245","parentId":"wrk_0d9db9250da5438aab4956e39e8371c3","modified":1711639959822,"created":1711639956314,"url":"http://localhost:3000/api/forums","name":"forums","description":"","method":"GET","body":{},"preRequestScript":"","parameters":[],"headers":[{"name":"User-Agent","value":"insomnia/8.6.1"}],"authentication":{},"metaSortKey":-1711393119697,"isPrivate":false,"pathParameters":[],"settingStoreCookies":true,"settingSendCookies":true,"settingDisableRenderRequestBody":false,"settingEncodeUrl":true,"settingRebuildPath":true,"settingFollowRedirects":"global","_type":"request"},{"_id":"req_2a88a7994a7f4588a2e0db0b8ee9567c","parentId":"wrk_0d9db9250da5438aab4956e39e8371c3","modified":1713985103313,"created":1713467520642,"url":"http://localhost:3000/api/sujets/1/messages","name":"insert messages (sujets/id/messages)","description":"","method":"PUT","body":{"mimeType":"application/json","text":"{\n\t\"content\":\"insomnia\",\n\t\"author_id\":1,\n\t\"sujet_id\":1\n}"},"preRequestScript":"","parameters":[],"headers":[{"name":"Content-Type","value":"application/json"},{"name":"User-Agent","value":"insomnia/8.6.1"}],"authentication":{},"metaSortKey":-1711406792137.75,"isPrivate":false,"pathParameters":[],"settingStoreCookies":true,"settingSendCookies":true,"settingDisableRenderRequestBody":false,"settingEncodeUrl":true,"settingRebuildPath":true,"settingFollowRedirects":"global","_type":"request"},{"_id":"req_2863497891ce437e87d447b5c5eea367","parentId":"wrk_0d9db9250da5438aab4956e39e8371c3","modified":1713985122049,"created":1711786698829,"url":"http://localhost:3000/api/sujets","name":"insert sujets","description":"","method":"PUT","body":{"mimeType":"application/json","text":"{\n\t\"title\":\"title\",\n\t\"author\":1,\n\t\"forum\":4\n}"},"preRequestScript":"","parameters":[],"headers":[{"name":"Content-Type","value":"application/json"},{"name":"User-Agent","value":"insomnia/8.6.1"}],"authentication":{},"metaSortKey":-1711420464578.5,"isPrivate":false,"pathParameters":[],"settingStoreCookies":true,"settingSendCookies":true,"settingDisableRenderRequestBody":false,"settingEncodeUrl":true,"settingRebuildPath":true,"settingFollowRedirects":"global","_type":"request"},{"_id":"req_c0100b9d31a24ea5b326bdf7e7581307","parentId":"wrk_0d9db9250da5438aab4956e39e8371c3","modified":1711620784302,"created":1711620780323,"url":"http://localhost:3000/api/sujets","name":"sujets","description":"","method":"GET","body":{},"preRequestScript":"","parameters":[],"headers":[{"name":"User-Agent","value":"insomnia/8.6.1"}],"authentication":{},"metaSortKey":-1711447809460,"isPrivate":false,"pathParameters":[],"settingStoreCookies":true,"settingSendCookies":true,"settingDisableRenderRequestBody":false,"settingEncodeUrl":true,"settingRebuildPath":true,"settingFollowRedirects":"global","_type":"request"},{"_id":"req_3e51c97897b142d8838b51162b5fe6bb","parentId":"wrk_0d9db9250da5438aab4956e39e8371c3","modified":1713003164540,"created":1713003147560,"url":"http://localhost:3000/api/users","name":"update password user","description":"","method":"POST","body":{"mimeType":"application/json","text":"{\n\t\"login\": \"user\",\n\t\"password\": \"user\"\n}"},"preRequestScript":"","parameters":[],"headers":[{"name":"Content-Type","value":"application/json"},{"name":"User-Agent","value":"insomnia/8.6.1"}],"authentication":{},"metaSortKey":-1711475154341.5,"isPrivate":false,"pathParameters":[],"settingStoreCookies":true,"settingSendCookies":true,"settingDisableRenderRequestBody":false,"settingEncodeUrl":true,"settingRebuildPath":true,"settingFollowRedirects":"global","_type":"request"},{"_id":"req_a5d345d6adbe4480860dd726b6f70f68","parentId":"wrk_0d9db9250da5438aab4956e39e8371c3","modified":1714078410508,"created":1711647408885,"url":"http://localhost:3000/api/users","name":"insert users","description":"","method":"PUT","body":{"mimeType":"application/json","text":"{\n\t\"login\": \"admin\",\n\t\"password\": \"admin\",\n\t\"admin\": true\n}"},"preRequestScript":"","parameters":[],"headers":[{"name":"Content-Type","value":"application/json"},{"name":"User-Agent","value":"insomnia/8.6.1"}],"authentication":{},"metaSortKey":-1711502499223,"isPrivate":false,"pathParameters":[],"settingStoreCookies":true,"settingSendCookies":true,"settingDisableRenderRequestBody":false,"settingEncodeUrl":true,"settingRebuildPath":true,"settingFollowRedirects":"global","_type":"request"},{"_id":"req_3fa1acc1d6e74a599716e8ee5a084789","parentId":"wrk_0d9db9250da5438aab4956e39e8371c3","modified":1711557264810,"created":1711557188986,"url":"http://localhost:3000/api/users","name":"users","description":"","method":"GET","body":{},"preRequestScript":"","parameters":[],"headers":[{"name":"User-Agent","value":"insomnia/8.6.1"}],"authentication":{},"metaSortKey":-1711557188986,"isPrivate":false,"pathParameters":[],"settingStoreCookies":true,"settingSendCookies":true,"settingDisableRenderRequestBody":false,"settingEncodeUrl":true,"settingRebuildPath":true,"settingFollowRedirects":"global","_type":"request"},{"_id":"req_9b4c25d063094e4987919e3c9c5dad9c","parentId":"wrk_0d9db9250da5438aab4956e39e8371c3","modified":1713003179213,"created":1711642806903,"url":"http://localhost:3000/api/login","name":"login","description":"","method":"POST","body":{"mimeType":"application/json","text":"{\n\t\"login\": \"user\",\n\t\"password\": \"user\"\n}"},"preRequestScript":"","parameters":[],"headers":[{"name":"Content-Type","value":"application/json"},{"name":"User-Agent","value":"insomnia/8.6.1"}],"authentication":{},"metaSortKey":-1711642806903,"isPrivate":false,"pathParameters":[],"settingStoreCookies":true,"settingSendCookies":true,"settingDisableRenderRequestBody":false,"settingEncodeUrl":true,"settingRebuildPath":true,"settingFollowRedirects":"global","_type":"request"},{"_id":"req_52d2d4356e7e4198849cfdb9dbe66e7e","parentId":"wrk_0d9db9250da5438aab4956e39e8371c3","modified":1714077399984,"created":1714075210038,"url":"http://localhost:3000/api/generate","name":"Generate Data","description":"","method":"PUT","body":{"mimeType":"application/json","text":"{\n\t\"nbForumMin\":3,\n\t\"nbForumMax\":5,\n\t\"nbSujetMin\":5,\n\t\"nbSujetMax\":20,\n\t\"nbMessageMin\":5,\n\t\"nbMessageMax\":50,\n\t\"nbUser\":5,\n\t\"nbAdmin\":2\n}"},"preRequestScript":"","parameters":[],"headers":[{"name":"Content-Type","value":"application/json"},{"name":"User-Agent","value":"insomnia/9.0.0"}],"authentication":{},"metaSortKey":-1714075210038,"isPrivate":false,"pathParameters":[],"settingStoreCookies":true,"settingSendCookies":true,"settingDisableRenderRequestBody":false,"settingEncodeUrl":true,"settingRebuildPath":true,"settingFollowRedirects":"global","_type":"request"},{"_id":"req_d3dcc10ef6754eaeb5dba70e61e35920","parentId":"wrk_0d9db9250da5438aab4956e39e8371c3","modified":1714079180762,"created":1714078468126,"url":"http://localhost:3000/api/forums","name":"insert forum","description":"","method":"PUT","body":{"mimeType":"application/json","text":"{\n\t\"title\":\"title\",\n\t\"author_id\":1\n}"},"preRequestScript":"","parameters":[],"headers":[{"name":"Content-Type","value":"application/json"},{"name":"User-Agent","value":"insomnia/9.0.0"}],"authentication":{},"metaSortKey":-1714078468126,"isPrivate":false,"pathParameters":[],"settingStoreCookies":true,"settingSendCookies":true,"settingDisableRenderRequestBody":false,"settingEncodeUrl":true,"settingRebuildPath":true,"settingFollowRedirects":"global","_type":"request"},{"_id":"req_f9381166bc954b0e91b5b6bdfc919766","parentId":"wrk_0d9db9250da5438aab4956e39e8371c3","modified":1714079742664,"created":1714078660444,"url":"http://localhost:3000/api/forums/2","name":"delete forum","description":"","method":"DELETE","body":{},"preRequestScript":"","parameters":[],"headers":[{"name":"User-Agent","value":"insomnia/9.0.0"}],"authentication":{},"metaSortKey":-1714078660444,"isPrivate":false,"pathParameters":[],"settingStoreCookies":true,"settingSendCookies":true,"settingDisableRenderRequestBody":false,"settingEncodeUrl":true,"settingRebuildPath":true,"settingFollowRedirects":"global","_type":"request"},{"_id":"req_41f35b585f474847965147a6a8e19859","parentId":"wrk_0d9db9250da5438aab4956e39e8371c3","modified":1714150749848,"created":1714150497688,"url":"http://localhost:3000/api/sujets/93","name":"edit sujet","description":"","method":"POST","body":{"mimeType":"application/json","text":"{\n\t\"title\":\"modifié\"\n}"},"preRequestScript":"","parameters":[],"headers":[{"name":"Content-Type","value":"application/json"},{"name":"User-Agent","value":"insomnia/9.0.0"}],"authentication":{},"metaSortKey":-1714114535535.5,"isPrivate":false,"pathParameters":[],"settingStoreCookies":true,"settingSendCookies":true,"settingDisableRenderRequestBody":false,"settingEncodeUrl":true,"settingRebuildPath":true,"settingFollowRedirects":"global","_type":"request"},{"_id":"req_836bb6ceadbc441ea2499f571be81f49","parentId":"wrk_0d9db9250da5438aab4956e39e8371c3","modified":1714150511212,"created":1714150410627,"url":"http://localhost:3000/api/sujets/92","name":"delete sujet","description":"","method":"DELETE","body":{},"preRequestScript":"","parameters":[],"headers":[{"name":"User-Agent","value":"insomnia/9.0.0"}],"authentication":{},"metaSortKey":-1714150410627,"isPrivate":false,"pathParameters":[],"settingStoreCookies":true,"settingSendCookies":true,"settingDisableRenderRequestBody":false,"settingEncodeUrl":true,"settingRebuildPath":true,"settingFollowRedirects":"global","_type":"request"},{"_id":"env_990693b847ac6fec5e0d6b79fa308783a7e9421f","parentId":"wrk_0d9db9250da5438aab4956e39e8371c3","modified":1711557182283,"created":1711557182283,"name":"Base Environment","data":{},"dataPropertyOrder":null,"color":null,"isPrivate":false,"metaSortKey":1711557182283,"_type":"environment"},{"_id":"jar_990693b847ac6fec5e0d6b79fa308783a7e9421f","parentId":"wrk_0d9db9250da5438aab4956e39e8371c3","modified":1714150721145,"created":1711557182287,"name":"Default Jar","cookies":[{"key":"sessionId","value":"ufk2OCzJmFl7F8fTX3MsNz0fhMHzJw1nZnJMBQVAtomwMDvs6XLBuEds0qmAysQg","expires":"2024-04-26T17:08:39.000Z","domain":"localhost","path":"/","secure":true,"httpOnly":true,"hostOnly":true,"creation":"2024-04-01T14:21:14.734Z","lastAccessed":"2024-04-26T16:58:41.145Z","sameSite":"lax","id":"e04bf635-b4af-43a0-824c-f63bc8367cc7"}],"_type":"cookie_jar"}]}